spandrel_extra_arches/__helper.py
spandrel_extra_arches/__init__.py
spandrel_extra_arches/architectures/__init__.py
spandrel_extra_arches/architectures/AdaCode/__init__.py
spandrel_extra_arches/architectures/AdaCode/__arch/__init__.py
spandrel_extra_arches/architectures/AdaCode/__arch/adacode_contrast_arch.py
spandrel_extra_arches/architectures/CodeFormer/__init__.py
spandrel_extra_arches/architectures/CodeFormer/__arch/__init__.py
spandrel_extra_arches/architectures/CodeFormer/__arch/codeformer.py
spandrel_extra_arches/architectures/DDColor/__color.py
spandrel_extra_arches/architectures/DDColor/__init__.py
spandrel_extra_arches/architectures/DDColor/__arch/__init__.py
spandrel_extra_arches/architectures/DDColor/__arch/convnext.py
spandrel_extra_arches/architectures/DDColor/__arch/ddcolor.py
spandrel_extra_arches/architectures/DDColor/__arch/position_encoding.py
spandrel_extra_arches/architectures/DDColor/__arch/transformer.py
spandrel_extra_arches/architectures/DDColor/__arch/transformer_utils.py
spandrel_extra_arches/architectures/DDColor/__arch/unet.py
spandrel_extra_arches/architectures/FeMaSR/__init__.py
spandrel_extra_arches/architectures/FeMaSR/__arch/__init__.py
spandrel_extra_arches/architectures/FeMaSR/__arch/fema_utils.py
spandrel_extra_arches/architectures/FeMaSR/__arch/femasr.py
spandrel_extra_arches/architectures/M3SNet/__init__.py
spandrel_extra_arches/architectures/M3SNet/__arch/M3SNet.py
spandrel_extra_arches/architectures/M3SNet/__arch/__init__.py
spandrel_extra_arches/architectures/M3SNet/__arch/arch_utils.py
spandrel_extra_arches/architectures/M3SNet/__arch/local_arch.py
spandrel_extra_arches/architectures/MAT/__init__.py
spandrel_extra_arches/architectures/MAT/__arch/MAT.py
spandrel_extra_arches/architectures/MAT/__arch/__init__.py
spandrel_extra_arches/architectures/MAT/__arch/utils.py
spandrel_extra_arches/architectures/MIRNet2/__init__.py
spandrel_extra_arches/architectures/MIRNet2/__arch/__init__.py
spandrel_extra_arches-0.2.0.dist-info/METADATA
spandrel_extra_arches-0.2.0.dist-info/WHEEL
spandrel_extra_arches-0.2.0.dist-info/top_level.txt
spandrel_extra_arches-0.2.0.dist-info/RECORD
