Metadata-Version: 2.1
Name: spandrel_extra_arches
Version: 0.2.0
Summary: Implements extra model architectures for spandrel
Author: chaiNNer team
License: MIT
Keywords: spandrel,pytorch architecture,pytorch arch,model arch,model architecture
Classifier: Development Status :: 2 - Pre-Alpha
Classifier: Intended Audience :: Developers
Classifier: Topic :: Software Development :: Libraries
Classifier: Programming Language :: Python :: 3
Classifier: Programming Language :: Python :: 3.8
Classifier: Programming Language :: Python :: 3.9
Classifier: Programming Language :: Python :: 3.10
Classifier: Programming Language :: Python :: 3.11
Classifier: Programming Language :: Python :: 3.12
Classifier: Programming Language :: Python :: 3 :: Only
Classifier: License :: OSI Approved :: MIT License
Classifier: Operating System :: OS Independent
Requires-Python: >=3.8
Requires-Dist: spandrel >=0.3.2
Requires-Dist: torch
Requires-Dist: torchvision
Requires-Dist: numpy
Requires-Dist: einops
Requires-Dist: typing-extensions
